firefly_test-0.1.1.dist-info/METADATA
firefly_test-0.1.1.dist-info/WHEEL
firefly_test-0.1.1.dist-info/licenses/LICENSE
firefly_test.libs/libasound-56bcdd56.so.2
firefly_test.libs/libcap-0e62ac39.so.2
firefly_test.libs/libudev-5c27e740.so.1
firefly_test/__init__.py
firefly_test/_app.py
firefly_test/_cli.py
firefly_test/_color.py
firefly_test/_frame.py
firefly_test/_input.py
firefly_test/_rust.cpython-312-x86_64-linux-gnu.so
firefly_test/_rust.pyi
firefly_test/py.typed
firefly_test-0.1.1.dist-info/RECORD
