Metadata-Version: 2.4
Name: firefly-test
Version: 0.1.1
Classifier: Development Status :: 4 - Beta
Classifier: Framework :: Pytest
Classifier: Topic :: Software Development :: Testing
Classifier: Topic :: Games/Entertainment
Classifier: Programming Language :: Rust
Classifier: Programming Language :: Python :: Implementation :: CPython
Classifier: Programming Language :: Python :: Implementation :: PyPy
Requires-Dist: pytest ; extra == 'test'
Requires-Dist: pytest-cov ; extra == 'test'
Requires-Dist: ruff ; extra == 'lint'
Requires-Dist: mypy ; extra == 'lint'
Provides-Extra: test
Provides-Extra: lint
License-File: LICENSE
Summary: Framework for writing tests for Firefly Zero apps
Keywords: firefly-zero,firefly,pytest,testing,gamedev
Requires-Python: >=3.10
Project-URL: homepage, https://github.com/firefly-zero/firefly-test
Project-URL: repository, https://github.com/firefly-zero/firefly-test
